{"hash":"8d5a227dfacffb9d733fb96f7351c2f513dac11f","data":{"posts":{"totalCount":1,"pageInfo":{"totalPages":1,"currentPage":1},"edges":[{"node":{"id":"31ec2fb0d887c80bf4a692927d2ce81e","title":"How to Base64 Decode on Mac | IToolkit","categories":[{"id":"Base64","path":"/category/Base64/"}],"date":"October 18, 2021","summary":"Learn how to decode base64 on Mac using Terminal commands like base64 or free online Base64 decoder tools.","thumbnail":"https://miro.medium.com/v2/resize:fit:1400/format:webp/1*hzE_QoqVCUt66HzliEalNg.png","timeToRead":3,"path":"/how-to-base64-decode-on-mac"}}]}},"context":{}}